{
    "country_code":  "BEL",
    "country":  "Belgium",
    "most_frequent_topics":  [
                                 {
                                     "rank":  1,
                                     "text":  "Provide comprehensive software development assistance across multiple programming domains and technologies",
                                     "share":  20.442743919103581
                                 },
                                 {
                                     "rank":  2,
                                     "text":  "Provide educational tutoring and academic assistance across multiple subjects and disciplines",
                                     "share":  7.2424159606449852
                                 },
                                 {
                                     "rank":  3,
                                     "text":  "Help edit, improve, and create professional written documents and communications",
                                     "share":  6.0125717409128177
                                 },
                                 {
                                     "rank":  4,
                                     "text":  "Provide technical IT support and troubleshooting assistance",
                                     "share":  5.8759223831647995
                                 },
                                 {
                                     "rank":  5,
                                     "text":  "Help develop and debug complete web applications and user interfaces",
                                     "share":  5.5752937961191584
                                 },
                                 {
                                     "rank":  6,
                                     "text":  "Provide technical and academic assistance across scientific research and educational domains",
                                     "share":  5.5479639245695545
                                 },
                                 {
                                     "rank":  7,
                                     "text":  "Provide comprehensive financial guidance and investment assistance across multiple domains",
                                     "share":  4.9740366220278762
                                 },
                                 {
                                     "rank":  8,
                                     "text":  "Provide multilingual translation services and language learning assistance",
                                     "share":  3.470893686799672
                                 },
                                 {
                                     "rank":  9,
                                     "text":  "Provide comprehensive domestic life and household management guidance",
                                     "share":  3.361574200601257
                                 },
                                 {
                                     "rank":  10,
                                     "text":  "Analyze and process data from documents, visual media, and business sources",
                                     "share":  3.1429352282044278
                                 }
                             ],
    "job_groups":  [
                       {
                           "name":  "Computer and Mathematical",
                           "share":  25.034162339437003
                       },
                       {
                           "name":  "Office and Administrative Support",
                           "share":  6.09456135556163
                       },
                       {
                           "name":  "Educational Instruction and Library",
                           "share":  5.3566548237223284
                       },
                       {
                           "name":  "Arts, Design, Entertainment, Sports, and Media",
                           "share":  3.6348729160972955
                       },
                       {
                           "name":  "Life, Physical, and Social Science",
                           "share":  1.0385351188849412
                       },
                       {
                           "name":  "Community and Social Service",
                           "share":  0.54659743099207447
                       },
                       {
                           "name":  "Sales and Related",
                           "share":  0.491937687892867
                       },
                       {
                           "name":  "Architecture and Engineering",
                           "share":  0.40994807324405586
                       }
                   ]
}
